slack_notification/__init__.py
slack_notification/banner.py
slack_notification/singleton_base.py
slack_notification/slack_notification.py
slack_notification/version.py
slack_notification-0.1.8.dist-info/METADATA
slack_notification-0.1.8.dist-info/WHEEL
slack_notification-0.1.8.dist-info/licenses/LICENSE
slack_notification-0.1.8.dist-info/RECORD
